move_migrations/__init__.py
move_migrations/move_migrations.py
move_migrations/move_migrations_utils.py
move_migrations-0.1.0.dist-info/entry_points.txt
move_migrations-0.1.0.dist-info/WHEEL
move_migrations-0.1.0.dist-info/METADATA
move_migrations-0.1.0.dist-info/RECORD
